[
  {
    "name": "CAP",
    "color": "A0D9D9",
    "description": "https://classicalacademicpress.com/"
  },
  {
    "name": "ClassicalU",
    "color": "11174F",
    "description": "https://classicalu.com/"
  },
  {
    "name": "Scholé Academy",
    "color": "6B1328",
    "description": "https://scholeacademy.com/"
  },
  {
    "name": "bug",
    "color": "EF4444",
    "description": "unintended behavior"
  },
  {
    "name": "chore",
    "color": "D1D5DB",
    "description": "necessary work"
  },
  {
    "name": "feature",
    "color": "A7F3D0",
    "description": "chore + customer value"
  },
  {
    "name": "noop",
    "color": "FFFFFF",
    "description": "work invalidated"
  }
]
